simses/VERSION
simses/__init__.py
simses/analysis.defaults.ini
simses/data.defaults.ini
simses/logger.defaults.ini
simses/main.py
simses/simulation.defaults.ini
simses/analysis/__init__.py
simses/analysis/factory.py
simses/analysis/storage.py
simses/analysis/utils.py
simses/analysis/data/__init__.py
simses/analysis/data/abstract_data.py
simses/analysis/data/electrolyzer.py
simses/analysis/data/energy_management.py
simses/analysis/data/fuel_cell.py
simses/analysis/data/hydrogen.py
simses/analysis/data/lithium_ion.py
simses/analysis/data/redox_flow.py
simses/analysis/data/system.py
simses/analysis/evaluation/__init__.py
simses/analysis/evaluation/abstract_evaluation.py
simses/analysis/evaluation/merger.py
simses/analysis/evaluation/result.py
simses/analysis/evaluation/economic/__init__.py
simses/analysis/evaluation/economic/economic_evaluation.py
simses/analysis/evaluation/economic/revenue_stream/__init__.py
simses/analysis/evaluation/economic/revenue_stream/abstract_revenue_stream.py
simses/analysis/evaluation/economic/revenue_stream/demand_charge_reduction.py
simses/analysis/evaluation/economic/revenue_stream/electricity_consumption.py
simses/analysis/evaluation/economic/revenue_stream/energy_cost_reduction.py
simses/analysis/evaluation/economic/revenue_stream/fcr_revenue_stream.py
simses/analysis/evaluation/economic/revenue_stream/intraday_recharge.py
simses/analysis/evaluation/economic/revenue_stream/operation_and_maintenance.py
simses/analysis/evaluation/plotting/__init__.py
simses/analysis/evaluation/plotting/axis.py
simses/analysis/evaluation/plotting/energy_plotting.py
simses/analysis/evaluation/plotting/matplot_plotting.py
simses/analysis/evaluation/plotting/plotly_plotting.py
simses/analysis/evaluation/plotting/plotter.py
simses/analysis/evaluation/plotting/sankey_diagram.py
simses/analysis/evaluation/plotting/sunburst_diagram.py
simses/analysis/evaluation/plotting/system_parameters.py
simses/analysis/evaluation/technical/__init__.py
simses-1.3.4.dist-info/LICENSE.txt
simses-1.3.4.dist-info/METADATA
simses-1.3.4.dist-info/WHEEL
simses-1.3.4.dist-info/top_level.txt
simses-1.3.4.dist-info/RECORD
