Metadata-Version: 2.1
Name: simses
Version: 1.3.4
Summary: Simulation for Stationary Storage Systems (SimSES)
Author-email: simses.ees@ed.tum.de
License: BSD-3-Clause
Project-URL: source, https://gitlab.lrz.de/open-ees-ses/simses
Keywords: simulation,battery,energy,storage
Classifier: Development Status :: 5 - Production/Stable
Classifier: License :: OSI Approved :: BSD License
Classifier: Intended Audience :: Science/Research
Classifier: Topic :: Scientific/Engineering
Requires-Python: >=3.8
License-File: LICENSE.txt
Requires-Dist: scipy
Requires-Dist: numpy
Requires-Dist: numpy-financial
Requires-Dist: pandas
Requires-Dist: plotly
Requires-Dist: matplotlib
Requires-Dist: pytz
Provides-Extra: tests
Requires-Dist: pytest ; extra == 'tests'
